ansible_cmdb-1.31.data/data/lib/ansiblecmdb/ansible-cmdb.py
ansible_cmdb-1.31.data/data/lib/ansiblecmdb/data/VERSION
ansible_cmdb-1.31.data/data/lib/ansiblecmdb/data/static/images/sort_asc.png
ansible_cmdb-1.31.data/data/lib/ansiblecmdb/data/static/images/sort_both.png
ansible_cmdb-1.31.data/data/lib/ansiblecmdb/data/static/images/sort_desc.png
ansible_cmdb-1.31.data/data/lib/ansiblecmdb/data/static/js/jquery-1.10.2.min.js
ansible_cmdb-1.31.data/data/lib/ansiblecmdb/data/static/js/jquery.dataTables.css
ansible_cmdb-1.31.data/data/lib/ansiblecmdb/data/static/js/jquery.dataTables.js
ansible_cmdb-1.31.data/data/lib/ansiblecmdb/data/tpl/csv.tpl
ansible_cmdb-1.31.data/data/lib/ansiblecmdb/data/tpl/html_fancy.tpl
ansible_cmdb-1.31.data/data/lib/ansiblecmdb/data/tpl/html_fancy_defs.html
ansible_cmdb-1.31.data/data/lib/ansiblecmdb/data/tpl/html_fancy_split.py
ansible_cmdb-1.31.data/data/lib/ansiblecmdb/data/tpl/html_fancy_split_detail.tpl
ansible_cmdb-1.31.data/data/lib/ansiblecmdb/data/tpl/html_fancy_split_overview.tpl
ansible_cmdb-1.31.data/data/lib/ansiblecmdb/data/tpl/json.tpl
ansible_cmdb-1.31.data/data/lib/ansiblecmdb/data/tpl/markdown.tpl
ansible_cmdb-1.31.data/data/lib/ansiblecmdb/data/tpl/markdown_split.py
ansible_cmdb-1.31.data/data/lib/ansiblecmdb/data/tpl/markdown_split_detail.tpl
ansible_cmdb-1.31.data/data/lib/ansiblecmdb/data/tpl/markdown_split_overview.tpl
ansible_cmdb-1.31.data/data/lib/ansiblecmdb/data/tpl/sql.tpl
ansible_cmdb-1.31.data/data/lib/ansiblecmdb/data/tpl/txt_table.tpl
ansible_cmdb-1.31.data/scripts/ansible-cmdb
ansible_cmdb-1.31.dist-info/METADATA
ansible_cmdb-1.31.dist-info/RECORD
ansible_cmdb-1.31.dist-info/WHEEL
ansible_cmdb-1.31.dist-info/top_level.txt
ansiblecmdb/__init__.py
ansiblecmdb/ansible.py
ansiblecmdb/ihateyaml.py
ansiblecmdb/parser.py
ansiblecmdb/render.py
ansiblecmdb/util.py
ansiblecmdb/data/VERSION
ansiblecmdb/data/static/images/sort_asc.png
ansiblecmdb/data/static/images/sort_both.png
ansiblecmdb/data/static/images/sort_desc.png
ansiblecmdb/data/static/js/jquery-1.10.2.min.js
ansiblecmdb/data/static/js/jquery.dataTables.css
