Metadata-Version: 2.1
Name: ansible-cmdb
Version: 1.31
Summary: Generate host overview from ansible fact gathering output
Home-page: https://github.com/fboender/ansible-cmdb
Author: Ferry Boender
Author-email: ferry.boender@electricmonk.nl
License: GPLv3
Platform: UNKNOWN
Classifier: Development Status :: 5 - Production/Stable
Classifier: Environment :: Console
Classifier: Intended Audience :: Developers
Classifier: Intended Audience :: Information Technology
Classifier: Intended Audience :: System Administrators
Classifier: License :: OSI Approved :: GNU General Public License v3 (GPLv3)
Classifier: Natural Language :: English
Classifier: Operating System :: POSIX
Classifier: Programming Language :: Python
Classifier: Programming Language :: Python :: 2.6
Classifier: Programming Language :: Python :: 2.7
Classifier: Programming Language :: Python :: 3
Classifier: Topic :: System :: Installation/Setup
Classifier: Topic :: System :: Systems Administration
Classifier: Topic :: Utilities
Requires-Dist: mako
Requires-Dist: pyyaml
Requires-Dist: ushlex
Requires-Dist: jsonxs
